aesFile.py
AES_File_Encryption-2.0.0.3.dist-info/LICENSE
AES_File_Encryption-2.0.0.3.dist-info/METADATA
AES_File_Encryption-2.0.0.3.dist-info/WHEEL
AES_File_Encryption-2.0.0.3.dist-info/top_level.txt
AES_File_Encryption-2.0.0.3.dist-info/RECORD
