Metadata-Version: 2.1
Name: AES-File-Encryption
Version: 2.0.0.3
Summary: AES File Encryption/Decryption with password
Classifier: Programming Language :: Python :: 3
Classifier: License :: OSI Approved :: MIT License
Classifier: Operating System :: OS Independent
Requires-Python: >=3.6
License-File: LICENSE
Requires-Dist: pycryptodome (==3.15.0)
